LICENSE
README.md
setup.py
coinstac_dinunet/__init__.py
coinstac_dinunet/site_runner.py
coinstac_dinunet/trainer.py
coinstac_dinunet.egg-info/PKG-INFO
coinstac_dinunet.egg-info/SOURCES.txt
coinstac_dinunet.egg-info/dependency_links.txt
coinstac_dinunet.egg-info/requires.txt
coinstac_dinunet.egg-info/top_level.txt
coinstac_dinunet/config/__init__.py
coinstac_dinunet/config/keys.py
coinstac_dinunet/data/__init__.py
coinstac_dinunet/data/data.py
coinstac_dinunet/data/datautils.py
coinstac_dinunet/distrib/__init__.py
coinstac_dinunet/distrib/learner.py
coinstac_dinunet/distrib/reducer.py
coinstac_dinunet/distrib/nodes/__init__.py
coinstac_dinunet/distrib/nodes/local.py
coinstac_dinunet/distrib/nodes/remote.py
coinstac_dinunet/distrib/powersgd/__init__.py
coinstac_dinunet/distrib/rankdad/__init__.py
coinstac_dinunet/distrib/rankdad/spi.py
coinstac_dinunet/metrics/__init__.py
coinstac_dinunet/metrics/loss.py
coinstac_dinunet/metrics/metrics.py
coinstac_dinunet/nn/__init__.py
coinstac_dinunet/nn/basetrainer.py
coinstac_dinunet/utils/__init__.py
coinstac_dinunet/utils/logger.py
coinstac_dinunet/utils/tensorutils.py
coinstac_dinunet/utils/utils.py
coinstac_dinunet/vision/__init__.py
coinstac_dinunet/vision/imageutils.py
coinstac_dinunet/vision/plotter.py