Metadata-Version: 2.1
Name: coinstac-dinunet
Version: 2.5.1
Summary: Distributed Neural Network implementation on COINSTAC.
Home-page: https://github.com/trendscenter/coinstac-dinunet
Author: Aashis Khana1
Author-email: sraashis@gmail.com
License: MIT
Platform: UNKNOWN
Classifier: License :: OSI Approved :: MIT License
Classifier: Programming Language :: Python :: 3.6
Classifier: Programming Language :: Python :: 3.7
License-File: LICENSE
